README.md
setup.cfg
setup.py
pycheckoapi/__init__.py
pycheckoapi/__version__.py
pycheckoapi/api.py
pycheckoapi/exceptions.py
pycheckoapi/link.py
pycheckoapi.egg-info/PKG-INFO
pycheckoapi.egg-info/SOURCES.txt
pycheckoapi.egg-info/dependency_links.txt
pycheckoapi.egg-info/requires.txt
pycheckoapi.egg-info/top_level.txt