Metadata-Version: 2.1
Name: pycheckoapi
Version: 0.2.170125
Summary: Full implementation of checko.ru API functions in Python
Home-page: https://github.com/io451/pycheckoapi
Author: io451
Author-email: prvtangl@gmail.com
Keywords: osint
Classifier: Development Status :: 2 - Pre-Alpha
Classifier: Environment :: Console
Classifier: Intended Audience :: Developers
Classifier: License :: OSI Approved :: Mozilla Public License 2.0 (MPL 2.0)
Classifier: Natural Language :: Russian
Classifier: Operating System :: OS Independent
Classifier: Programming Language :: Python :: 3
Classifier: Programming Language :: Python :: 3.10
Classifier: Topic :: Internet :: WWW/HTTP
Classifier: Topic :: Internet :: WWW/HTTP :: Indexing/Search
Classifier: Topic :: Office/Business
Classifier: Topic :: Software Development :: Libraries
Requires-Python: >=3.10
Requires-Dist: requests>=2.25.1
